truescrub/__init__.py
truescrub/__main__.py
truescrub/api.py
truescrub/db.py
truescrub/highlights.py
truescrub/matchmaking.py
truescrub/models.py
truescrub/wsgi.py
truescrub/htdocs/vendor/highcharts-8.0.0.js
truescrub/htdocs/vendor/highcharts-more-8.0.0.js
truescrub/templates/index.html
truescrub/templates/leaderboard.html
truescrub/templates/macros.html
truescrub/templates/matchmaking.html
truescrub/templates/profile.html
truescrub/templates/skill_groups.html
truescrub/updater/__init__.py
truescrub/updater/__main__.py
truescrub/updater/evaluator.py
truescrub/updater/players.ini
truescrub/updater/recalculate.py
truescrub/updater/state_parser.py
truescrub/updater/updater.py
truescrub-0.1.0.dist-info/LICENSE
truescrub-0.1.0.dist-info/METADATA
truescrub-0.1.0.dist-info/WHEEL
truescrub-0.1.0.dist-info/entry_points.txt
truescrub-0.1.0.dist-info/top_level.txt
truescrub-0.1.0.dist-info/RECORD
