Metadata-Version: 2.1
Name: truescrub
Version: 0.1.0
Summary: UNKNOWN
Home-page: UNKNOWN
Author: Trevor Caira
Author-email: trevor@caira.com
License: UNKNOWN
Platform: UNKNOWN
Classifier: Programming Language :: Python :: 3
Classifier: License :: OSI Approved :: MIT License
Classifier: Operating System :: OS Independent
Requires-Dist: Flask (==1.1.1)
Requires-Dist: waitress (==1.4.3)
Requires-Dist: trueskill (==0.4.5)
Requires-Dist: pyzmq (==19.0.0)
Requires-Dist: werkzeug (==1.0.0)
